editor.py
setup.py
python_editor.egg-info/PKG-INFO
python_editor.egg-info/SOURCES.txt
python_editor.egg-info/dependency_links.txt
python_editor.egg-info/top_level.txt